alfred/__init__.py
alfred/logger.py
alfred/twingenio.py
twingenio_alfred-1.0.7.dist-info/METADATA
twingenio_alfred-1.0.7.dist-info/WHEEL
twingenio_alfred-1.0.7.dist-info/top_level.txt
twingenio_alfred-1.0.7.dist-info/RECORD
