Metadata-Version: 2.1
Name: twingenio_alfred
Version: 1.0.7
Summary: Client di Twingenio
Home-page: https://github.com/Twingenio/alfred
Author: hypertrue
Author-email: info@hypertrue.com
Classifier: Programming Language :: Python :: 3
Classifier: Operating System :: OS Independent
Requires-Python: >=3.11
Requires-Dist: aiohttp==3.10.0
Requires-Dist: Flask==3.0.3
Requires-Dist: Flask-Login==0.6.3
Requires-Dist: pydantic==2.8.2
Requires-Dist: Requests==2.32.3
